faultit/__init__.py
faultit/apply.py
faultit/blame.py
faultit/change.py
faultit/hunk_utils.py
faultit/main.py
faultit/match_lines.py
faultit-0.1.0.dist-info/entry_points.txt
faultit-0.1.0.dist-info/LICENSE
faultit-0.1.0.dist-info/WHEEL
faultit-0.1.0.dist-info/METADATA
faultit-0.1.0.dist-info/RECORD
