Metadata-Version: 2.1
Name: faultit
Version: 0.1.0
Summary: 
Author: shahar.yarn
Author-email: shahar.yarn@gmail.com
Requires-Python: >=3.8,<4.0
Classifier: Programming Language :: Python :: 3
Classifier: Programming Language :: Python :: 3.10
Classifier: Programming Language :: Python :: 3.8
Classifier: Programming Language :: Python :: 3.9
Requires-Dist: click (>=8.1.3,<9.0.0)
Requires-Dist: pygit2 (>=1.9.2,<2.0.0)
